client/__init__.py
client/client.py
client/client/__init__.py
client/client/add_contact.py
client/client/client_database.py
client/client/client_socket.py
client/client/del_contact.py
client/client/main_window.py
client/client/main_window_conv.py
client/client/start_dialog.py
client/client/common/__init__.py
client/client/common/alerts.py
client/client/common/constants.py
client/client/common/decorators.py
client/client/common/functions.py
client/client/logs/__init__.py
client/client/logs/config_client_log.py
messenger_gb_client-0.0.1.data/scripts/client_run
messenger_gb_client-0.0.1.dist-info/METADATA
messenger_gb_client-0.0.1.dist-info/WHEEL
messenger_gb_client-0.0.1.dist-info/top_level.txt
messenger_gb_client-0.0.1.dist-info/RECORD
