Metadata-Version: 2.1
Name: messenger-gb-client
Version: 0.0.1
Summary: messenger_gb_client
Home-page: UNKNOWN
Author: Alexey Kh
Author-email: mraxe@bk.ru
License: UNKNOWN
Platform: UNKNOWN
Requires-Dist: PyQt5
Requires-Dist: sqlalchemy
Requires-Dist: pycryptodome
Requires-Dist: pycryptodomex
